retrytools/__init__.py
retrytools/core.py
retrytools-0.0.3.post1.dist-info/METADATA
retrytools-0.0.3.post1.dist-info/WHEEL
retrytools-0.0.3.post1.dist-info/licenses/LICENSE
retrytools-0.0.3.post1.dist-info/RECORD
